sdapy/__init__.py
sdapy/__version__.py
sdapy/constants.py
sdapy/corner_hack.py
sdapy/filters.py
sdapy/functions.py
sdapy/gaussian_process.py
sdapy/image_tool.py
sdapy/interaction_processes.py
sdapy/model_fitters.py
sdapy/pbar.py
sdapy/plot_atlas_fp.py
sdapy/read_default.py
sdapy/sneGui.py
sdapy/snerun.py
sdapy/specline_handler.py
sdapy/data/auth.txt
sdapy/data/bc_table.txt
sdapy/data/bts_meta.txt
sdapy/data/bts_meta_old.txt
sdapy/data/c10_template.txt
sdapy/data/csm_table.txt
sdapy/data/default_par.txt
sdapy/data/individual_par.txt
sdapy/data/logo.txt
sdapy/data/oac_meta.txt
sdapy/data/filter_transmission/ztf_g_band.csv
sdapy/data/filter_transmission/ztf_i_band.csv
sdapy/data/filter_transmission/ztf_r_band.csv
sdapy/data/salt2-4/salt2_color_correction.dat
sdapy/data/salt2-4/salt2_color_dispersion.dat
sdapy/data/salt2-4/salt2_lc_dispersion_scaling.dat
sdapy/data/salt2-4/salt2_lc_relative_covariance_01.dat
sdapy/data/salt2-4/salt2_lc_relative_variance_0.dat
sdapy/data/salt2-4/salt2_lc_relative_variance_1.dat
sdapy/data/salt2-4/salt2_spec_covariance_01.dat
sdapy/data/salt2-4/salt2_spec_variance_0.dat
sdapy/data/salt2-4/salt2_spec_variance_1.dat
sdapy/data/salt2-4/salt2_template_0.dat
sdapy/data/salt2-4/salt2_template_1.dat
sdapy/engines/__init__.py
sdapy/engines/bol_early.py
sdapy/engines/bol_full.py
sdapy/engines/bol_main.py
sdapy/engines/bol_tail.py
sdapy/engines/multiband_early.py
sdapy/engines/multiband_main.py
sdapy/engines/sed.py
sdapy/engines/specline.py
sdapy/engines/specv_evolution.py
sdapy/models/__init__.py
sdapy/models/arnett_tail/__init__.py
sdapy/models/arnett_tail/functions.py
sdapy/models/arnett_tail/parameters.py
sdapy/models/bazin/__init__.py
sdapy/models/bazin/functions.py
sdapy/models/bazin/parameters.py
sdapy/models/blackbody/__init__.py
sdapy/models/blackbody/functions.py
sdapy/models/blackbody/parameters.py
sdapy/models/csm/__init__.py
sdapy/models/csm/functions.py
sdapy/models/csm/parameters.py
sdapy/models/exponential/__init__.py
HAFFET-0.1.2.dist-info/LICENSE
HAFFET-0.1.2.dist-info/METADATA
HAFFET-0.1.2.dist-info/WHEEL
HAFFET-0.1.2.dist-info/entry_points.txt
HAFFET-0.1.2.dist-info/top_level.txt
HAFFET-0.1.2.dist-info/RECORD
